{
  "version": 1,
  "serviceConfiguration": {
    "apiName": "flutter3",
    "serviceName": "AppSync",
    "gqlSchemaPath": "/tmp/amplify-9c720926-a3d0-4c23-96db-4312dbb5809f/amplify/backend/api/flutter3/schema.graphql",
    "defaultAuthType": {
      "mode": "AMAZON_COGNITO_USER_POOLS",
      "cognitoUserPoolId": "authflutter3"
    },
    "additionalAuthTypes": [
      {
        "mode": "AWS_IAM"
      },
      {
        "mode": "API_KEY",
        "keyDescription": "api key description",
        "expirationTime": 30
      }
    ],
    "conflictResolution": {
      "defaultResolutionStrategy": {
        "type": "AUTOMERGE"
      }
    }
  }
}